Metadata-Version: 1.0
Name: RKnumbersgame
Version: 1.0
Summary: Number guessing game
Home-page: UNKNOWN
Author: Rohan Krishnakumar
Author-email: rohankrishnakumar3@gmail.com
License: UNKNOWN
Platform: UNKNOWN
